email_stuff.py
email_stuff-0.1.0.dist-info/LICENSE
email_stuff-0.1.0.dist-info/METADATA
email_stuff-0.1.0.dist-info/WHEEL
email_stuff-0.1.0.dist-info/top_level.txt
email_stuff-0.1.0.dist-info/RECORD
