Metadata-Version: 2.1
Name: email-stuff
Version: 0.1.0
Summary: Email sending functionality package
Home-page: https://github.com/george-oconnor/email-stuff
Author: george.oconnor (George O' Connor)
Author-email: <george@georgeoc.com>
Keywords: python,email,outlook,send email,email attachments,mail,gmail,smtp
Classifier: Development Status :: 4 - Beta
Classifier: Intended Audience :: Developers
Classifier: Programming Language :: Python :: 3
Classifier: Operating System :: OS Independent
Classifier: License :: OSI Approved :: MIT License
License-File: LICENSE
